{
    "feature": "attr2_num",
    "threshold": 435.6758879595834,
    "children": {
        "<=": {
            "feature": "attr5_num",
            "threshold": 65322.35941320293,
            "children": {
                "<=": {
                    "feature": "attr2_num",
                    "threshold": 316.70346665586857,
                    "children": {
                        "<=": {
                            "feature": "attr2_num",
                            "threshold": 287.789494085849,
                            "children": {
                                "<=": {
                                    "feature": "attr1_num",
                                    "threshold": 43778.53191489362,
                                    "children": {
                                        "<=": {
                                            "label": 0
                                        },
                                        ">": {
                                            "label": 0
                                        }
                                    }
                                },
                                ">": {
                                    "label": 0
                                }
                            }
                        },
                        ">": {
                            "feature": "attr7_num",
                            "threshold": 939.7157757009346,
                            "children": {
                                "<=": {
                                    "feature": "attr2_num",
                                    "threshold": 332.47000425892855,
                                    "children": {
                                        "<=": {
                                            "label": 0
                                        },
                                        ">": {
                                            "label": 0
                                        }
                                    }
                                },
                                ">": {
                                    "feature": "attr6_num",
                                    "threshold": 0.709160558627451,
                                    "children": {
                                        "<=": {
                                            "label": 0
                                        },
                                        ">": {
                                            "label": 0
                                        }
                                    }
                                }
                            }
                        }
                    }
                },
                ">": {
                    "feature": "attr6_num",
                    "threshold": 0.7071482177142856,
                    "children": {
                        "<=": {
                            "feature": "attr1_num",
                            "threshold": 74631.91208791209,
                            "children": {
                                "<=": {
                                    "feature": "attr3_num",
                                    "threshold": 229.81711390408162,
                                    "children": {
                                        "<=": {
                                            "label": 0
                                        },
                                        ">": {
                                            "label": 0
                                        }
                                    }
                                },
                                ">": {
                                    "feature": "attr3_num",
                                    "threshold": 255.2857883261905,
                                    "children": {
                                        "<=": {
                                            "label": 1
                                        },
                                        ">": {
                                            "label": 1
                                        }
                                    }
                                }
                            }
                        },
                        ">": {
                            "feature": "attr5_num",
                            "threshold": 79373.09523809524,
                            "children": {
                                "<=": {
                                    "feature": "attr7_num",
                                    "threshold": 1037.0321694915256,
                                    "children": {
                                        "<=": {
                                            "label": 0
                                        },
                                        ">": {
                                            "label": 0
                                        }
                                    }
                                },
                                ">": {
                                    "feature": "attr1_num",
                                    "threshold": 85493.47826086957,
                                    "children": {
                                        "<=": {
                                            "label": 0
                                        },
                                        ">": {
                                            "label": 1
                                        }
                                    }
                                }
                            }
                        }
                    }
                }
            }
        },
        ">": {
            "feature": "attr7_num",
            "threshold": 1424.8923344051448,
            "children": {
                "<=": {
                    "feature": "attr1_num",
                    "threshold": 97997.24277456648,
                    "children": {
                        "<=": {
                            "feature": "attr2_num",
                            "threshold": 468.1801445406594,
                            "children": {
                                "<=": {
                                    "feature": "attr7_num",
                                    "threshold": 1193.0228333333334,
                                    "children": {
                                        "<=": {
                                            "label": 1
                                        },
                                        ">": {
                                            "label": 1
                                        }
                                    }
                                },
                                ">": {
                                    "feature": "attr6_num",
                                    "threshold": 0.669941769081081,
                                    "children": {
                                        "<=": {
                                            "label": 1
                                        },
                                        ">": {
                                            "label": 1
                                        }
                                    }
                                }
                            }
                        },
                        ">": {
                            "feature": "attr7_num",
                            "threshold": 1333.129012195122,
                            "children": {
                                "<=": {
                                    "feature": "attr3_num",
                                    "threshold": 280.2399534325,
                                    "children": {
                                        "<=": {
                                            "label": 1
                                        },
                                        ">": {
                                            "label": 1
                                        }
                                    }
                                },
                                ">": {
                                    "feature": "attr4_num",
                                    "threshold": 0.8246753018809523,
                                    "children": {
                                        "<=": {
                                            "label": 1
                                        },
                                        ">": {
                                            "label": 1
                                        }
                                    }
                                }
                            }
                        }
                    }
                },
                ">": {
                    "feature": "attr7_num",
                    "threshold": 1612.9682173913043,
                    "children": {
                        "<=": {
                            "label": 1
                        },
                        ">": {
                            "feature": "attr2_num",
                            "threshold": 685.0766948892857,
                            "children": {
                                "<=": {
                                    "label": 1
                                },
                                ">": {
                                    "feature": "attr2_num",
                                    "threshold": 752.3880104954546,
                                    "children": {
                                        "<=": {
                                            "label": 1
                                        },
                                        ">": {
                                            "label": 1
                                        }
                                    }
                                }
                            }
                        }
                    }
                }
            }
        }
    }
}