{
    "feature": "attr2_num",
    "threshold": 431.86403639916665,
    "children": {
        "<=": {
            "feature": "attr2_num",
            "threshold": 347.8608491054455,
            "children": {
                "<=": {
                    "feature": "attr7_num",
                    "threshold": 891.941504854369,
                    "children": {
                        "<=": {
                            "feature": "attr7_num",
                            "threshold": 822.9925368421052,
                            "children": {
                                "<=": {
                                    "label": 0
                                },
                                ">": {
                                    "feature": "attr4_num",
                                    "threshold": 0.73672889872,
                                    "children": {
                                        "<=": {
                                            "label": 0
                                        },
                                        ">": {
                                            "label": 0
                                        }
                                    }
                                }
                            }
                        },
                        ">": {
                            "feature": "attr5_num",
                            "threshold": 61058.84684684685,
                            "children": {
                                "<=": {
                                    "feature": "attr3_num",
                                    "threshold": 218.24895435138887,
                                    "children": {
                                        "<=": {
                                            "label": 0
                                        },
                                        ">": {
                                            "label": 0
                                        }
                                    }
                                },
                                ">": {
                                    "feature": "attr2_num",
                                    "threshold": 336.7199251564103,
                                    "children": {
                                        "<=": {
                                            "label": 0
                                        },
                                        ">": {
                                            "label": 0
                                        }
                                    }
                                }
                            }
                        }
                    }
                },
                ">": {
                    "feature": "attr4_num",
                    "threshold": 0.7721258520454544,
                    "children": {
                        "<=": {
                            "feature": "attr2_num",
                            "threshold": 381.72924655316456,
                            "children": {
                                "<=": {
                                    "feature": "attr1_num",
                                    "threshold": 74293.72340425532,
                                    "children": {
                                        "<=": {
                                            "label": 0
                                        },
                                        ">": {
                                            "label": 0
                                        }
                                    }
                                },
                                ">": {
                                    "feature": "attr7_num",
                                    "threshold": 1151.8667500000001,
                                    "children": {
                                        "<=": {
                                            "label": 0
                                        },
                                        ">": {
                                            "label": 1
                                        }
                                    }
                                }
                            }
                        },
                        ">": {
                            "feature": "attr7_num",
                            "threshold": 1047.4521596638651,
                            "children": {
                                "<=": {
                                    "feature": "attr6_num",
                                    "threshold": 0.6908475864210526,
                                    "children": {
                                        "<=": {
                                            "label": 0
                                        },
                                        ">": {
                                            "label": 0
                                        }
                                    }
                                },
                                ">": {
                                    "feature": "attr7_num",
                                    "threshold": 1108.885322580645,
                                    "children": {
                                        "<=": {
                                            "label": 0
                                        },
                                        ">": {
                                            "label": 1
                                        }
                                    }
                                }
                            }
                        }
                    }
                }
            }
        },
        ">": {
            "feature": "attr3_num",
            "threshold": 289.80336595569617,
            "children": {
                "<=": {
                    "feature": "attr1_num",
                    "threshold": 98420.17045454546,
                    "children": {
                        "<=": {
                            "feature": "attr2_num",
                            "threshold": 463.87308289090913,
                            "children": {
                                "<=": {
                                    "feature": "attr5_num",
                                    "threshold": 87781.08474576271,
                                    "children": {
                                        "<=": {
                                            "label": 1
                                        },
                                        ">": {
                                            "label": 1
                                        }
                                    }
                                },
                                ">": {
                                    "feature": "attr6_num",
                                    "threshold": 0.639580047375,
                                    "children": {
                                        "<=": {
                                            "label": 1
                                        },
                                        ">": {
                                            "label": 1
                                        }
                                    }
                                }
                            }
                        },
                        ">": {
                            "feature": "attr1_num",
                            "threshold": 114055.93506493507,
                            "children": {
                                "<=": {
                                    "label": 1
                                },
                                ">": {
                                    "feature": "attr6_num",
                                    "threshold": 0.6576438401515152,
                                    "children": {
                                        "<=": {
                                            "label": 1
                                        },
                                        ">": {
                                            "label": 1
                                        }
                                    }
                                }
                            }
                        }
                    }
                },
                ">": {
                    "feature": "attr6_num",
                    "threshold": 0.7028413745571428,
                    "children": {
                        "<=": {
                            "feature": "attr6_num",
                            "threshold": 0.6406471345294117,
                            "children": {
                                "<=": {
                                    "feature": "attr7_num",
                                    "threshold": 1892.8640526315787,
                                    "children": {
                                        "<=": {
                                            "label": 1
                                        },
                                        ">": {
                                            "label": 0
                                        }
                                    }
                                },
                                ">": {
                                    "feature": "attr7_num",
                                    "threshold": 1497.0285625000001,
                                    "children": {
                                        "<=": {
                                            "label": 1
                                        },
                                        ">": {
                                            "label": 1
                                        }
                                    }
                                }
                            }
                        },
                        ">": {
                            "feature": "attr2_num",
                            "threshold": 573.3057478134831,
                            "children": {
                                "<=": {
                                    "feature": "attr6_num",
                                    "threshold": 0.7311202558780487,
                                    "children": {
                                        "<=": {
                                            "label": 1
                                        },
                                        ">": {
                                            "label": 1
                                        }
                                    }
                                },
                                ">": {
                                    "label": 1
                                }
                            }
                        }
                    }
                }
            }
        }
    }
}