{
    "feature": "attr5_num",
    "threshold": 92640.64444444445,
    "children": {
        "<=": {
            "feature": "attr1_num",
            "threshold": 64204.32522123894,
            "children": {
                "<=": {
                    "feature": "attr2_num",
                    "threshold": 317.99560185662097,
                    "children": {
                        "<=": {
                            "feature": "attr1_num",
                            "threshold": 46001.90291262136,
                            "children": {
                                "<=": {
                                    "feature": "attr3_num",
                                    "threshold": 191.08907655555555,
                                    "children": {
                                        "<=": {
                                            "label": 0
                                        },
                                        ">": {
                                            "label": 0
                                        }
                                    }
                                },
                                ">": {
                                    "feature": "attr3_num",
                                    "threshold": 224.74835222653064,
                                    "children": {
                                        "<=": {
                                            "label": 0
                                        },
                                        ">": {
                                            "label": 0
                                        }
                                    }
                                }
                            }
                        },
                        ">": {
                            "feature": "attr2_num",
                            "threshold": 345.42571344396555,
                            "children": {
                                "<=": {
                                    "feature": "attr7_num",
                                    "threshold": 923.4373384615384,
                                    "children": {
                                        "<=": {
                                            "label": 0
                                        },
                                        ">": {
                                            "label": 0
                                        }
                                    }
                                },
                                ">": {
                                    "feature": "attr6_num",
                                    "threshold": 0.7066869777843137,
                                    "children": {
                                        "<=": {
                                            "label": 0
                                        },
                                        ">": {
                                            "label": 0
                                        }
                                    }
                                }
                            }
                        }
                    }
                },
                ">": {
                    "feature": "attr2_num",
                    "threshold": 406.0512220566523,
                    "children": {
                        "<=": {
                            "feature": "attr7_num",
                            "threshold": 1056.2054033613445,
                            "children": {
                                "<=": {
                                    "feature": "attr5_num",
                                    "threshold": 70702.765625,
                                    "children": {
                                        "<=": {
                                            "label": 0
                                        },
                                        ">": {
                                            "label": 0
                                        }
                                    }
                                },
                                ">": {
                                    "feature": "attr1_num",
                                    "threshold": 78052.14545454546,
                                    "children": {
                                        "<=": {
                                            "label": 0
                                        },
                                        ">": {
                                            "label": 0
                                        }
                                    }
                                }
                            }
                        },
                        ">": {
                            "feature": "attr7_num",
                            "threshold": 1152.640447368421,
                            "children": {
                                "<=": {
                                    "feature": "attr4_num",
                                    "threshold": 0.8366860476470587,
                                    "children": {
                                        "<=": {
                                            "label": 0
                                        },
                                        ">": {
                                            "label": 1
                                        }
                                    }
                                },
                                ">": {
                                    "feature": "attr4_num",
                                    "threshold": 0.8417658131111111,
                                    "children": {
                                        "<=": {
                                            "label": 1
                                        },
                                        ">": {
                                            "label": 1
                                        }
                                    }
                                }
                            }
                        }
                    }
                }
            }
        },
        ">": {
            "feature": "attr1_num",
            "threshold": 131216.48880597015,
            "children": {
                "<=": {
                    "feature": "attr2_num",
                    "threshold": 501.66417419235677,
                    "children": {
                        "<=": {
                            "feature": "attr2_num",
                            "threshold": 465.43310227471267,
                            "children": {
                                "<=": {
                                    "feature": "attr1_num",
                                    "threshold": 96930.68421052632,
                                    "children": {
                                        "<=": {
                                            "label": 1
                                        },
                                        ">": {
                                            "label": 1
                                        }
                                    }
                                },
                                ">": {
                                    "feature": "attr1_num",
                                    "threshold": 103290.20408163265,
                                    "children": {
                                        "<=": {
                                            "label": 1
                                        },
                                        ">": {
                                            "label": 1
                                        }
                                    }
                                }
                            }
                        },
                        ">": {
                            "feature": "attr3_num",
                            "threshold": 270.49317591428576,
                            "children": {
                                "<=": {
                                    "label": 1
                                },
                                ">": {
                                    "feature": "attr5_num",
                                    "threshold": 126533.53125,
                                    "children": {
                                        "<=": {
                                            "label": 1
                                        },
                                        ">": {
                                            "label": 1
                                        }
                                    }
                                }
                            }
                        }
                    }
                },
                ">": {
                    "feature": "attr6_num",
                    "threshold": 0.707138883144144,
                    "children": {
                        "<=": {
                            "feature": "attr7_num",
                            "threshold": 1700.2765714285715,
                            "children": {
                                "<=": {
                                    "label": 1
                                },
                                ">": {
                                    "feature": "attr3_num",
                                    "threshold": 335.290055525,
                                    "children": {
                                        "<=": {
                                            "label": 0
                                        },
                                        ">": {
                                            "label": 1
                                        }
                                    }
                                }
                            }
                        },
                        ">": {
                            "label": 1
                        }
                    }
                }
            }
        }
    }
}