{
    "feature": "attr2_num",
    "threshold": 440.81315943819453,
    "children": {
        "<=": {
            "feature": "attr5_num",
            "threshold": 66245.31818181818,
            "children": {
                "<=": {
                    "feature": "attr3_num",
                    "threshold": 208.61621991306532,
                    "children": {
                        "<=": {
                            "feature": "attr2_num",
                            "threshold": 311.32111538080807,
                            "children": {
                                "<=": {
                                    "label": 0
                                },
                                ">": {
                                    "feature": "attr7_num",
                                    "threshold": 914.6058235294119,
                                    "children": {
                                        "<=": {
                                            "label": 0
                                        },
                                        ">": {
                                            "label": 0
                                        }
                                    }
                                }
                            }
                        },
                        ">": {
                            "feature": "attr2_num",
                            "threshold": 321.748594062,
                            "children": {
                                "<=": {
                                    "feature": "attr6_num",
                                    "threshold": 0.7158338722444444,
                                    "children": {
                                        "<=": {
                                            "label": 0
                                        },
                                        ">": {
                                            "label": 0
                                        }
                                    }
                                },
                                ">": {
                                    "feature": "attr4_num",
                                    "threshold": 0.7530932412727273,
                                    "children": {
                                        "<=": {
                                            "label": 0
                                        },
                                        ">": {
                                            "label": 0
                                        }
                                    }
                                }
                            }
                        }
                    }
                },
                ">": {
                    "feature": "attr2_num",
                    "threshold": 390.7268356360407,
                    "children": {
                        "<=": {
                            "feature": "attr4_num",
                            "threshold": 0.7075338679081634,
                            "children": {
                                "<=": {
                                    "feature": "attr6_num",
                                    "threshold": 0.7250607015333332,
                                    "children": {
                                        "<=": {
                                            "label": 0
                                        },
                                        ">": {
                                            "label": 0
                                        }
                                    }
                                },
                                ">": {
                                    "feature": "attr1_num",
                                    "threshold": 70019.90566037736,
                                    "children": {
                                        "<=": {
                                            "label": 0
                                        },
                                        ">": {
                                            "label": 0
                                        }
                                    }
                                }
                            }
                        },
                        ">": {
                            "feature": "attr6_num",
                            "threshold": 0.7036882661313132,
                            "children": {
                                "<=": {
                                    "feature": "attr6_num",
                                    "threshold": 0.6685072820476191,
                                    "children": {
                                        "<=": {
                                            "label": 1
                                        },
                                        ">": {
                                            "label": 0
                                        }
                                    }
                                },
                                ">": {
                                    "feature": "attr2_num",
                                    "threshold": 413.7248867210526,
                                    "children": {
                                        "<=": {
                                            "label": 0
                                        },
                                        ">": {
                                            "label": 1
                                        }
                                    }
                                }
                            }
                        }
                    }
                }
            }
        },
        ">": {
            "feature": "attr3_num",
            "threshold": 293.55657743641973,
            "children": {
                "<=": {
                    "feature": "attr2_num",
                    "threshold": 509.5539545299435,
                    "children": {
                        "<=": {
                            "feature": "attr5_num",
                            "threshold": 96883.50892857143,
                            "children": {
                                "<=": {
                                    "feature": "attr1_num",
                                    "threshold": 83770.88679245283,
                                    "children": {
                                        "<=": {
                                            "label": 1
                                        },
                                        ">": {
                                            "label": 1
                                        }
                                    }
                                },
                                ">": {
                                    "feature": "attr7_num",
                                    "threshold": 1281.8942881355933,
                                    "children": {
                                        "<=": {
                                            "label": 1
                                        },
                                        ">": {
                                            "label": 1
                                        }
                                    }
                                }
                            }
                        },
                        ">": {
                            "label": 1
                        }
                    }
                },
                ">": {
                    "feature": "attr7_num",
                    "threshold": 1586.5294421768706,
                    "children": {
                        "<=": {
                            "feature": "attr4_num",
                            "threshold": 0.7878587736582278,
                            "children": {
                                "<=": {
                                    "feature": "attr7_num",
                                    "threshold": 1384.562512195122,
                                    "children": {
                                        "<=": {
                                            "label": 1
                                        },
                                        ">": {
                                            "label": 1
                                        }
                                    }
                                },
                                ">": {
                                    "label": 1
                                }
                            }
                        },
                        ">": {
                            "feature": "attr6_num",
                            "threshold": 0.719092773735294,
                            "children": {
                                "<=": {
                                    "feature": "attr6_num",
                                    "threshold": 0.6463744969090908,
                                    "children": {
                                        "<=": {
                                            "label": 1
                                        },
                                        ">": {
                                            "label": 1
                                        }
                                    }
                                },
                                ">": {
                                    "label": 1
                                }
                            }
                        }
                    }
                }
            }
        }
    }
}