{
    "feature": "attr7_num",
    "threshold": 1173.7697986111111,
    "children": {
        "<=": {
            "feature": "attr2_num",
            "threshold": 350.16810095521623,
            "children": {
                "<=": {
                    "feature": "attr2_num",
                    "threshold": 311.7928114756219,
                    "children": {
                        "<=": {
                            "feature": "attr7_num",
                            "threshold": 846.7350224719102,
                            "children": {
                                "<=": {
                                    "feature": "attr5_num",
                                    "threshold": 43396.07894736842,
                                    "children": {
                                        "<=": {
                                            "label": 0
                                        },
                                        ">": {
                                            "label": 0
                                        }
                                    }
                                },
                                ">": {
                                    "feature": "attr5_num",
                                    "threshold": 54189.17647058824,
                                    "children": {
                                        "<=": {
                                            "label": 0
                                        },
                                        ">": {
                                            "label": 0
                                        }
                                    }
                                }
                            }
                        },
                        ">": {
                            "feature": "attr2_num",
                            "threshold": 331.2265536357143,
                            "children": {
                                "<=": {
                                    "feature": "attr3_num",
                                    "threshold": 215.9261744241936,
                                    "children": {
                                        "<=": {
                                            "label": 0
                                        },
                                        ">": {
                                            "label": 0
                                        }
                                    }
                                },
                                ">": {
                                    "feature": "attr4_num",
                                    "threshold": 0.7338438694199999,
                                    "children": {
                                        "<=": {
                                            "label": 0
                                        },
                                        ">": {
                                            "label": 0
                                        }
                                    }
                                }
                            }
                        }
                    }
                },
                ">": {
                    "feature": "attr6_num",
                    "threshold": 0.7020531601927084,
                    "children": {
                        "<=": {
                            "feature": "attr6_num",
                            "threshold": 0.6660291270681818,
                            "children": {
                                "<=": {
                                    "feature": "attr1_num",
                                    "threshold": 67496.35555555555,
                                    "children": {
                                        "<=": {
                                            "label": 0
                                        },
                                        ">": {
                                            "label": 0
                                        }
                                    }
                                },
                                ">": {
                                    "feature": "attr7_num",
                                    "threshold": 1067.4019767441862,
                                    "children": {
                                        "<=": {
                                            "label": 0
                                        },
                                        ">": {
                                            "label": 1
                                        }
                                    }
                                }
                            }
                        },
                        ">": {
                            "feature": "attr1_num",
                            "threshold": 74398.85576923077,
                            "children": {
                                "<=": {
                                    "feature": "attr4_num",
                                    "threshold": 0.7971177232244898,
                                    "children": {
                                        "<=": {
                                            "label": 0
                                        },
                                        ">": {
                                            "label": 1
                                        }
                                    }
                                },
                                ">": {
                                    "feature": "attr5_num",
                                    "threshold": 84302.23636363636,
                                    "children": {
                                        "<=": {
                                            "label": 0
                                        },
                                        ">": {
                                            "label": 0
                                        }
                                    }
                                }
                            }
                        }
                    }
                }
            }
        },
        ">": {
            "feature": "attr7_num",
            "threshold": 1408.501250764526,
            "children": {
                "<=": {
                    "feature": "attr3_num",
                    "threshold": 265.53035416387434,
                    "children": {
                        "<=": {
                            "feature": "attr2_num",
                            "threshold": 481.2261070247423,
                            "children": {
                                "<=": {
                                    "feature": "attr7_num",
                                    "threshold": 1209.8830862068965,
                                    "children": {
                                        "<=": {
                                            "label": 1
                                        },
                                        ">": {
                                            "label": 1
                                        }
                                    }
                                },
                                ">": {
                                    "label": 1
                                }
                            }
                        },
                        ">": {
                            "feature": "attr7_num",
                            "threshold": 1286.3054148936171,
                            "children": {
                                "<=": {
                                    "feature": "attr1_num",
                                    "threshold": 97046.0,
                                    "children": {
                                        "<=": {
                                            "label": 1
                                        },
                                        ">": {
                                            "label": 1
                                        }
                                    }
                                },
                                ">": {
                                    "feature": "attr2_num",
                                    "threshold": 490.2809580340427,
                                    "children": {
                                        "<=": {
                                            "label": 1
                                        },
                                        ">": {
                                            "label": 1
                                        }
                                    }
                                }
                            }
                        }
                    }
                },
                ">": {
                    "feature": "attr4_num",
                    "threshold": 0.8401329086617646,
                    "children": {
                        "<=": {
                            "label": 1
                        },
                        ">": {
                            "feature": "attr6_num",
                            "threshold": 0.6711880168815789,
                            "children": {
                                "<=": {
                                    "feature": "attr2_num",
                                    "threshold": 644.1800972374999,
                                    "children": {
                                        "<=": {
                                            "label": 1
                                        },
                                        ">": {
                                            "label": 1
                                        }
                                    }
                                },
                                ">": {
                                    "label": 1
                                }
                            }
                        }
                    }
                }
            }
        }
    }
}