{
    "feature": "attr1_num",
    "threshold": 89041.37222222223,
    "children": {
        "<=": {
            "feature": "attr2_num",
            "threshold": 360.5544502833713,
            "children": {
                "<=": {
                    "feature": "attr1_num",
                    "threshold": 52782.004385964916,
                    "children": {
                        "<=": {
                            "feature": "attr2_num",
                            "threshold": 294.59884213508775,
                            "children": {
                                "<=": {
                                    "label": 0
                                },
                                ">": {
                                    "feature": "attr4_num",
                                    "threshold": 0.7766119685538462,
                                    "children": {
                                        "<=": {
                                            "label": 0
                                        },
                                        ">": {
                                            "label": 0
                                        }
                                    }
                                }
                            }
                        },
                        ">": {
                            "feature": "attr5_num",
                            "threshold": 62379.98245614035,
                            "children": {
                                "<=": {
                                    "feature": "attr3_num",
                                    "threshold": 218.85718407285714,
                                    "children": {
                                        "<=": {
                                            "label": 0
                                        },
                                        ">": {
                                            "label": 0
                                        }
                                    }
                                },
                                ">": {
                                    "feature": "attr7_num",
                                    "threshold": 1001.1903863636363,
                                    "children": {
                                        "<=": {
                                            "label": 0
                                        },
                                        ">": {
                                            "label": 0
                                        }
                                    }
                                }
                            }
                        }
                    }
                },
                ">": {
                    "feature": "attr4_num",
                    "threshold": 0.7988691804928909,
                    "children": {
                        "<=": {
                            "feature": "attr3_num",
                            "threshold": 254.56333870918365,
                            "children": {
                                "<=": {
                                    "feature": "attr6_num",
                                    "threshold": 0.7155513989285716,
                                    "children": {
                                        "<=": {
                                            "label": 0
                                        },
                                        ">": {
                                            "label": 0
                                        }
                                    }
                                },
                                ">": {
                                    "feature": "attr7_num",
                                    "threshold": 1108.5208333333333,
                                    "children": {
                                        "<=": {
                                            "label": 0
                                        },
                                        ">": {
                                            "label": 0
                                        }
                                    }
                                }
                            }
                        },
                        ">": {
                            "feature": "attr3_num",
                            "threshold": 227.60604278141594,
                            "children": {
                                "<=": {
                                    "feature": "attr7_num",
                                    "threshold": 1084.5789803921568,
                                    "children": {
                                        "<=": {
                                            "label": 0
                                        },
                                        ">": {
                                            "label": 1
                                        }
                                    }
                                },
                                ">": {
                                    "feature": "attr7_num",
                                    "threshold": 1157.5419677419354,
                                    "children": {
                                        "<=": {
                                            "label": 0
                                        },
                                        ">": {
                                            "label": 1
                                        }
                                    }
                                }
                            }
                        }
                    }
                }
            }
        },
        ">": {
            "feature": "attr2_num",
            "threshold": 549.6463307996441,
            "children": {
                "<=": {
                    "feature": "attr1_num",
                    "threshold": 106199.10126582278,
                    "children": {
                        "<=": {
                            "feature": "attr5_num",
                            "threshold": 100383.53846153847,
                            "children": {
                                "<=": {
                                    "feature": "attr3_num",
                                    "threshold": 273.34163795272724,
                                    "children": {
                                        "<=": {
                                            "label": 1
                                        },
                                        ">": {
                                            "label": 1
                                        }
                                    }
                                },
                                ">": {
                                    "label": 1
                                }
                            }
                        },
                        ">": {
                            "feature": "attr7_num",
                            "threshold": 1381.670104477612,
                            "children": {
                                "<=": {
                                    "feature": "attr3_num",
                                    "threshold": 292.9298386114286,
                                    "children": {
                                        "<=": {
                                            "label": 1
                                        },
                                        ">": {
                                            "label": 1
                                        }
                                    }
                                },
                                ">": {
                                    "label": 1
                                }
                            }
                        }
                    }
                },
                ">": {
                    "feature": "attr6_num",
                    "threshold": 0.6864080044634147,
                    "children": {
                        "<=": {
                            "feature": "attr7_num",
                            "threshold": 1661.003923076923,
                            "children": {
                                "<=": {
                                    "label": 1
                                },
                                ">": {
                                    "feature": "attr3_num",
                                    "threshold": 322.0154131571429,
                                    "children": {
                                        "<=": {
                                            "label": 1
                                        },
                                        ">": {
                                            "label": 1
                                        }
                                    }
                                }
                            }
                        },
                        ">": {
                            "label": 1
                        }
                    }
                }
            }
        }
    }
}